event_flow/application_schema/__init__.py
event_flow/application_schema/action_type.py
event_flow/application_schema/application.py
event_flow/application_schema/asyncapi_schema.py
event_flow/application_schema/channel.py
event_flow/application_schema/channel_schema.py
event_flow/application_schema/components.py
event_flow/application_schema/info_schema.py
event_flow/application_schema/message/__init__.py
event_flow/application_schema/message/binding/__init__.py
event_flow/application_schema/message/binding/amqp.py
event_flow/application_schema/message/binding/http.py
event_flow/application_schema/message/binding/kafka.py
event_flow/application_schema/message/event.py
event_flow/application_schema/message/example.py
event_flow/application_schema/message/header.py
event_flow/application_schema/message/message.py
event_flow/application_schema/message/message_meta.py
event_flow/application_schema/message/message_schema.py
event_flow/application_schema/message/payload.py
event_flow/application_schema/message/trait.py
event_flow/application_schema/operation.py
event_flow/application_schema/operation_schema.py
event_flow/application_schema/reference.py
event_flow/application_schema/tag.py
event_flow/sdk/__init__.py
event_flow/sdk/application/__init__.py
event_flow/sdk/application/channel/__init__.py
event_flow/sdk/application/channel/action_type.py
event_flow/sdk/application/channel/channel.py
event_flow/sdk/application/channel/operation.py
event_flow/sdk/application/event_flow.py
event_flow/sdk/application/message/__init__.py
event_flow/sdk/application/message/header.py
event_flow/sdk/application/message/message.py
event_flow/sdk/application/message/payload.py
event_flow/sdk/events/__init__.py
event_flow/sdk/events/dispatcher.py
event_flow/sdk/events/publisher.py
event_flow/sdk/events/routing_headers.py
event_flow/sdk/messaging/__init__.py
event_flow/sdk/messaging/consumer.py
event_flow/sdk/messaging/producer.py
event_flow/sdk/utils/__init__.py
event_flow_sdk-0.1.0.dist-info/METADATA
event_flow_sdk-0.1.0.dist-info/WHEEL
event_flow_sdk-0.1.0.dist-info/licenses/LICENSE
event_flow_sdk-0.1.0.dist-info/RECORD
