Metadata-Version: 2.1
Name: event-flow-sdk
Version: 0.1.0
Summary: Asynchronous Communication Framework
Author-Email: Valentin Vorobyev <voro6yov.valentin@gmail.com>
License: Apache License 2.0
Requires-Python: >=3.10
Requires-Dist: pydantic>=2.5.2
